quantrl_lab/__init__.py
quantrl_lab/backtesting/__init__.py
quantrl_lab/backtesting/analysis.py
quantrl_lab/backtesting/config/__init__.py
quantrl_lab/backtesting/config/algorithm_config.py
quantrl_lab/backtesting/config/config_registry.py
quantrl_lab/backtesting/config/reward_config.py
quantrl_lab/backtesting/config/reward_presets.py
quantrl_lab/backtesting/evaluation.py
quantrl_lab/backtesting/runner.py
quantrl_lab/backtesting/training.py
quantrl_lab/custom_envs/__init__.py
quantrl_lab/custom_envs/core/__init__.py
quantrl_lab/custom_envs/core/actions.py
quantrl_lab/custom_envs/core/config.py
quantrl_lab/custom_envs/core/portfolio.py
quantrl_lab/custom_envs/core/trading_env.py
quantrl_lab/custom_envs/stock/__init__.py
quantrl_lab/custom_envs/stock/env_single_stock.py
quantrl_lab/custom_envs/stock/stock_config.py
quantrl_lab/custom_envs/stock/stock_portfolio.py
quantrl_lab/custom_envs/stock/strategies/__init__.py
quantrl_lab/custom_envs/stock/strategies/actions/__init__.py
quantrl_lab/custom_envs/stock/strategies/actions/base_action.py
quantrl_lab/custom_envs/stock/strategies/actions/standard_market_action_strategy.py
quantrl_lab/custom_envs/stock/strategies/observations/__init__.py
quantrl_lab/custom_envs/stock/strategies/observations/base_observation.py
quantrl_lab/custom_envs/stock/strategies/observations/portfolio_w_trend_observation.py
quantrl_lab/custom_envs/stock/strategies/rewards/__init__.py
quantrl_lab/custom_envs/stock/strategies/rewards/base_reward.py
quantrl_lab/custom_envs/stock/strategies/rewards/cash_flow_risk_reward.py
quantrl_lab/custom_envs/stock/strategies/rewards/excessive_cash_penalty.py
quantrl_lab/custom_envs/stock/strategies/rewards/hold_penalty.py
quantrl_lab/custom_envs/stock/strategies/rewards/invalid_action_penalty.py
quantrl_lab/custom_envs/stock/strategies/rewards/portfolio_reward.py
quantrl_lab/custom_envs/stock/strategies/rewards/position_sizing_reward.py
quantrl_lab/custom_envs/stock/strategies/rewards/trend_following_reward.py
quantrl_lab-0.1.0.dist-info/METADATA
quantrl_lab-0.1.0.dist-info/WHEEL
quantrl_lab-0.1.0.dist-info/licenses/LICENSE
quantrl_lab-0.1.0.dist-info/RECORD
