Metadata-Version: 2.4
Name: quantrl-lab
Version: 0.1.0
Summary: A lightweight Python library for developing and backtesting RL Agents in financial markets
License: MIT
License-File: LICENSE
Keywords: reinforcement-learning,trading,finance,quantitative,backtesting,gymnasium,stable-baselines3
Author: whanyu1212
Author-email: whanyu1212@hotmail.com
Requires-Python: >=3.10,<4.0
Classifier: Development Status :: 3 - Alpha
Classifier: Intended Audience :: Developers
Classifier: Intended Audience :: Financial and Insurance Industry
Classifier: Intended Audience :: Science/Research
Classifier: License :: OSI Approved :: MIT License
Classifier: Programming Language :: Python :: 3
Classifier: Programming Language :: Python :: 3.10
Classifier: Programming Language :: Python :: 3.11
Classifier: Topic :: Scientific/Engineering :: Artificial Intelligence
Classifier: Topic :: Office/Business :: Financial :: Investment
Classifier: Operating System :: OS Independent
Requires-Dist: alpaca-py (>=0.40.1,<0.41.0)
Requires-Dist: black (>=25.1.0,<26.0.0)
Requires-Dist: docformatter (>=1.7.7,<2.0.0)
Requires-Dist: flake8 (>=7.2.0,<8.0.0)
Requires-Dist: gymnasium (>=1.1.1,<2.0.0)
Requires-Dist: iprogress (>=0.4,<0.5)
Requires-Dist: ipykernel (>=6.29.5,<7.0.0)
Requires-Dist: ipywidgets (>=8.1.7,<9.0.0)
Requires-Dist: isort (>=6.0.1,<7.0.0)
Requires-Dist: litellm (>=1.75.8,<2.0.0)
Requires-Dist: loguru (>=0.7.3,<0.8.0)
Requires-Dist: matplotlib (>=3.10.3,<4.0.0)
Requires-Dist: mypy (>=1.16.0,<2.0.0)
Requires-Dist: nbformat (>=5.10.4,<6.0.0)
Requires-Dist: numpy (>=2.2.6,<3.0.0)
Requires-Dist: openai (==1.99.9)
Requires-Dist: optuna (>=4.4.0,<5.0.0)
Requires-Dist: optuna-dashboard (>=0.19.0,<0.20.0)
Requires-Dist: optuna-integration (>=4.4.0,<5.0.0)
Requires-Dist: pandas (>=2.2.3,<3.0.0)
Requires-Dist: pre-commit (>=4.2.0,<5.0.0)
Requires-Dist: pyarrow (>=20.0.0,<21.0.0)
Requires-Dist: pydantic (>=2.11.7,<3.0.0)
Requires-Dist: pytest (>=8.4.0,<9.0.0)
Requires-Dist: python-dotenv (>=1.1.0,<2.0.0)
Requires-Dist: rich (>=14.0.0,<15.0.0)
Requires-Dist: scikit-learn (>=1.7.0,<2.0.0)
Requires-Dist: seaborn (>=0.13.2,<0.14.0)
Requires-Dist: stable-baselines3 (>=2.6.0,<3.0.0)
Requires-Dist: torch (>=2.7.1,<3.0.0)
Requires-Dist: transformers (>=4.53.1,<5.0.0)
Requires-Dist: yfinance (>=0.2.61,<0.3.0)
